utipy/__init__.py
utipy/array/__init__.py
utipy/array/blend.py
utipy/array/nan_stats.py
utipy/array/window.py
utipy/array/windowed_reverse.py
utipy/groups/__init__.py
utipy/groups/fold.py
utipy/groups/group.py
utipy/groups/group_uniques.py
utipy/groups/methods/__init__.py
utipy/groups/methods/l_sizes.py
utipy/groups/methods/n_dist.py
utipy/groups/partition.py
utipy/measures/__init__.py
utipy/measures/iqr.py
utipy/pandas/__init__.py
utipy/pandas/distort.py
utipy/pandas/drop.py
utipy/pandas/makes_up.py
utipy/pandas/move_column_inplace.py
utipy/pandas/polynomializer.py
utipy/pandas/resemble.py
utipy/pandas/subset_by_levels.py
utipy/path/__init__.py
utipy/path/iopaths.py
utipy/path/mk_rm_dir.py
utipy/path/prepare_paths.py
utipy/string/__init__.py
utipy/string/letter_strings.py
utipy/string/random_strings.py
utipy/time/__init__.py
utipy/time/format_time.py
utipy/time/timer.py
utipy/time/timestamps.py
utipy/utils/__init__.py
utipy/utils/check_instance.py
utipy/utils/convert_to_df.py
utipy/utils/convert_to_type.py
utipy/utils/extended_describe.py
utipy/utils/messenger.py
utipy/utils/step_idx.py
utipy-1.0.5.dist-info/LICENSE
utipy-1.0.5.dist-info/METADATA
utipy-1.0.5.dist-info/WHEEL
utipy-1.0.5.dist-info/RECORD
