Metadata-Version: 2.3
Name: utipy
Version: 1.0.5
Summary: Utility functions for python
License: MIT
Keywords: pandas,numpy,array,ndarray,groups,folds,kfold,partitioning,utilities,logging,time,tools,rolling,windows,time
Author: Ludvig
Author-email: <mail@ludvigolsen.dk>
Requires-Python: >=3.7,<4.0
Classifier: License :: OSI Approved :: MIT License
Classifier: Programming Language :: Python :: 3
Classifier: Programming Language :: Python :: 3.7
Classifier: Programming Language :: Python :: 3.8
Classifier: Programming Language :: Python :: 3.9
Classifier: Programming Language :: Python :: 3.10
Classifier: Programming Language :: Python :: 3.11
Classifier: Programming Language :: Python :: 3.12
Classifier: Programming Language :: Python :: 3.13
Requires-Dist: numpy (>=1.21.6,<2.0.0)
Requires-Dist: pandas (>=1.3.5,<2.0.0)
Project-URL: Changelog, https://github.com/ludvigolsen/utipy/blob/main/CHANGELOG.md
Project-URL: Issues, https://github.com/ludvigolsen/utipy/issues
Project-URL: Repository, https://github.com/ludvigolsen/utipy
